Workbook

Sheet TAM summary
A1: TAM summary
A2: Top-down TAM by bucket — FY24 through FY26, with OBBA reconciliation breakout
A3: All figures in USD thousands ($K)
A4: # | B4: Bucket | C4: FY24 Actual | D4: FY25 Enacted | E4: FY26 Request | F4: FY26 OBBA | G4: FY26 Total | H4: % of Full TAM | I4: % of In-Service
A5: 1 | B5: New Construction | C5: 28427000 | D5: 38453000 | E5: 19822000 | F5: 26507000 | G5: 46326000 | H5: =G5/G13 -> 0.61822784 | I5: —
A6: 2 | B6: Scheduled Depot Maintenance & Repair | C6: 13271718 | D6: 12909097 | E6: 13617194 | F6: 0 | G6: 13617194 | H6: =G6/G13 -> 0.18172362 | I6: =G6/G12 -> 0.47600019
A7: 3 | B7: Continuous / Intermediate / Emergent | C7: 2083638 | D7: 2155459 | E7: 2234715 | F7: 0 | G7: 2234715 | H7: =G7/G13 -> 0.029822627 | I7: =G7/G12 -> 0.078116297
A8: 4 | B8: Modernization & Alteration Installation | C8: 5505882 | D8: 5994559 | E8: 6624111 | F8: 0 | G8: 6624111 | H8: =G8/G13 -> 0.088399815 | I8: =G8/G12 -> 0.23155124
A9: 5 | B9: Major Life-Cycle Events (RCOH/SLEP/MMA) | C9: 210612 | D9: 1661363 | E9: 2492740 | F9: 0 | G9: 2492740 | H9: =G9/G13 -> 0.033266012 | I9: =G9/G12 -> 0.087135772
A10: 6 | B10: Sustainment Engineering / Planning | C10: 3192575 | D10: 3143211 | E10: 3411003 | F10: 0 | G10: 3411003 | H10: =G10/G13 -> 0.045520378 | I10: =G10/G12 -> 0.11923441
A11: 7 | B11: Availability Support / Port Services | C11: 254506 | D11: 226912 | E11: 227776 | F11: 0 | G11: 227776 | H11: =G11/G13 -> 0.003039707 | I11: =G11/G12 -> 0.007962097
B12: In-Service (Buckets 2–7) | C12: =SUM(C6:C11) -> 24518931 | D12: =SUM(D6:D11) -> 26090601 | E12: =SUM(E6:E11) -> 28607539 | F12: =SUM(F6:F11) -> 0 | G12: =SUM(G6:G11) -> 28607539
B13: Full TAM | C13: =SUM(C5:C11) -> 52945931 | D13: =SUM(D5:D11) -> 64543601 | E13: =SUM(E5:E11) -> 48429539 | F13: =SUM(F5:F11) -> 26507000 | G13: =SUM(G5:G11) -> 74933539

Sheet By vessel class
A1: By vessel class
A2: FY26 spending by vessel class and bucket — budget book data only, no analyst estimates
A3: All figures in USD thousands ($K), FY26
A4: Vessel Class | B4: B1 Request | C4: B1 OBBA | D4: B1 Total | E4: B2 | F4: B3 | G4: B4 | H4: B5 | I4: B6 | J4: B7 | K4: Row Total
A5: Navy Submarines
A6: SSBN (Columbia) | B6: 8994594 | C6: 1925892 | D6: 10920486 | E6: N/A | F6: N/A | G6: N/A | H6: N/A | I6: N/A | J6: N/A | K6: =SUM(D6:J6) -> 10920486
A7: SSN (Virginia) | B7: 4760225 | C7: 6317804 | D7: 11078029 | E7: N/A | F7: N/A | G7: N/A | H7: N/A | I7: N/A | J7: N/A | K7: =SUM(D7:J7) -> 11078029
A8: SSN/SSBN (in-service) | B8: 0 | C8: 0 | D8: 0 | E8: 1566819 | F8: N/A | G8: 766254 | H8: 0 | I8: 0 | J8: N/A | K8: =SUM(D8:J8) -> 2333073
A9: Navy Surface
A10: CVN (Nimitz/Ford) | B10: 3281673 | C10: 0 | D10: 3281673 | E10: 784000 | F10: N/A | G10: 0 | H10: 2274311 | I10: 86561 | J10: N/A | K10: =SUM(D10:J10) -> 6426545
A11: DDG-51 | B11: 10773 | C11: 5400000 | D11: 5410773 | E11: 749000 | F11: N/A | G11: 997485 | H11: 0 | I11: 0 | J11: N/A | K11: =SUM(D11:J11) -> 7157258
A12: DDG-1000 | B12: 52358 | C12: 0 | D12: 52358 | E12: 0 | F12: N/A | G12: 115267 | H12: 0 | I12: 209225 | J12: N/A | K12: =SUM(D12:J12) -> 376850
A13: CG (Ticonderoga) | B13: 0 | C13: 0 | D13: 0 | E13: 0 | F13: N/A | G13: 0 | H13: 0 | I13: 0 | J13: N/A | K13: =SUM(D13:J13) -> 0
A14: FFG-62 | B14: 0 | C14: 0 | D14: 0 | E14: 0 | F14: N/A | G14: 0 | H14: 0 | I14: 0 | J14: N/A | K14: =SUM(D14:J14) -> 0
A15: LCS | B15: 0 | C15: 0 | D15: 0 | E15: 492493 | F15: N/A | G15: 374321 | H15: 0 | I15: 0 | J15: N/A | K15: =SUM(D15:J15) -> 866814
A16: Navy Amphibious
A17: Amphibious (combined) | B17: 0 | C17: 0 | D17: 0 | E17: 624506 | F17: N/A | G17: 0 | H17: 0 | I17: 0 | J17: N/A | K17: =SUM(D17:J17) -> 624506
A18: LPD Flight II | B18: 0 | C18: 2600000 | D18: 2600000 | E18: N/A | F18: N/A | G18: 125542 | H18: 0 | I18: 0 | J18: N/A | K18: =SUM(D18:J18) -> 2725542
A19: LHA | B19: 0 | C19: 3895000 | D19: 3895000 | E19: N/A | F19: N/A | G19: 123384 | H19: 0 | I19: 0 | J19: N/A | K19: =SUM(D19:J19) -> 4018384
A20: LSD | B20: 0 | C20: 0 | D20: 0 | E20: N/A | F20: N/A | G20: 4079 | H20: 0 | I20: 0 | J20: N/A | K20: =SUM(D20:J20) -> 4079
A21: LSM | B21: 0 | C21: 1963941 | D21: 1963941 | E21: 0 | F21: N/A | G21: 0 | H21: 0 | I21: 0 | J21: N/A | K21: =SUM(D21:J21) -> 1963941
A22: Navy Auxiliaries
A23: T-AO (John Lewis) | B23: 8346 | C23: 1853359 | D23: 1861705 | E23: 0 | F23: N/A | G23: 0 | H23: 0 | I23: 0 | J23: N/A | K23: =SUM(D23:J23) -> 1861705
A24: T-AGOS | B24: 612205 | C24: 0 | D24: 612205 | E24: 0 | F24: N/A | G24: 0 | H24: 0 | I24: 0 | J24: N/A | K24: =SUM(D24:J24) -> 612205
A25: SSC/LCAC | B25: 0 | C25: 239095 | D25: 239095 | E25: 0 | F25: N/A | G25: 20321 | H25: 37883 | I25: 0 | J25: N/A | K25: =SUM(D25:J25) -> 297299
A26: LCU 1700 | B26: 0 | C26: 295000 | D26: 295000 | E26: 0 | F26: N/A | G26: 0 | H26: 0 | I26: 0 | J26: N/A | K26: =SUM(D26:J26) -> 295000
A27: Sealift (Strategic + Used) | B27: 45000 | C27: 700000 | D27: 745000 | E27: 0 | F27: N/A | G27: 0 | H27: 0 | I27: 0 | J27: N/A | K27: =SUM(D27:J27) -> 745000
A28: LCC | B28: 0 | C28: 0 | D28: 0 | E28: 0 | F28: N/A | G28: 0 | H28: 19276 | I28: 0 | J28: N/A | K28: =SUM(D28:J28) -> 19276
A29: ESB/ESD | B29: 0 | C29: 0 | D29: 0 | E29: 0 | F29: N/A | G29: 0 | H29: 0 | I29: 0 | J29: N/A | K29: =SUM(D29:J29) -> 0
A30: MSC Fleet | B30: 0 | C30: 0 | D30: 0 | E30: 1584000 | F30: N/A | G30: 0 | H30: 0 | I30: 0 | J30: N/A | K30: =SUM(D30:J30) -> 1584000
A31: Service Craft / APL | B31: 34602 | C31: 0 | D31: 34602 | E31: 0 | F31: N/A | G31: 0 | H31: 0 | I31: 0 | J31: N/A | K31: =SUM(D31:J31) -> 34602
A32: Coast Guard
A33: CG: OPC (Heritage) | B33: 812400 | C33: 0 | D33: 812400 | E33: 0 | F33: N/A | G33: 0 | H33: 0 | I33: 0 | J33: N/A | K33: =SUM(D33:J33) -> 812400
A34: CG: FRC (Sentinel) | B34: 216000 | C34: 0 | D34: 216000 | E34: 0 | F34: N/A | G34: 0 | H34: 0 | I34: 0 | J34: N/A | K34: =SUM(D34:J34) -> 216000
A35: CG: PSC / WCC / Icebreaker | B35: 228000 | C35: 0 | D35: 228000 | E35: 0 | F35: N/A | G35: 0 | H35: 0 | I35: 0 | J35: N/A | K35: =SUM(D35:J35) -> 228000
A36: CG: WMEC-270 | B36: 0 | C36: 0 | D36: 0 | E36: N/A | F36: N/A | G36: 0 | H36: 76000 | I36: 0 | J36: N/A | K36: =SUM(D36:J36) -> 76000
A37: CG: WLM-175 | B37: 0 | C37: 0 | D37: 0 | E37: N/A | F37: N/A | G37: 0 | H37: 15000 | I37: 0 | J37: N/A | K37: =SUM(D37:J37) -> 15000
A38: CG: MLB-47 | B38: 0 | C38: 0 | D38: 0 | E38: N/A | F38: N/A | G38: 0 | H38: 45000 | I38: 0 | J38: N/A | K38: =SUM(D38:J38) -> 45000
A39: CG: Healy / WMSL | B39: 0 | C39: 0 | D39: 0 | E39: N/A | F39: N/A | G39: 0 | H39: 16000 | I39: 0 | J39: N/A | K39: =SUM(D39:J39) -> 16000
A40: CG: RB-M | B40: 0 | C40: 0 | D40: 0 | E40: N/A | F40: N/A | G40: 0 | H40: 9270 | I40: 0 | J40: N/A | K40: =SUM(D40:J40) -> 9270
A41: Multi-class
A42: Outfitting (all newbuild) | B42: 863846 | C42: 23449 | D42: 887295 | E42: 0 | F42: N/A | G42: 0 | H42: 0 | I42: 0 | J42: N/A | K42: =SUM(D42:J42) -> 887295
A43: PY Completion (multi-class) | B43: 725429 | C43: 466837 | D43: 1192266 | E43: 0 | F43: N/A | G43: 0 | H43: 0 | I43: 0 | J43: N/A | K43: =SUM(D43:J43) -> 1192266
A44: CG In-service
A45: CG: In-service O&S | B45: 0 | C45: 0 | D45: 0 | E45: 369358 | F45: 246238 | G45: 52900 | H45: 0 | I45: 16000 | J45: N/A | K45: =SUM(D45:J45) -> 684496
A46: Subtotal (allocated) | B46: =B6+B7+B8+B10+B11+B12+B13+B14+B15+B17+B18+B19+B20+B21+B23+B24+B25+B26+B27+B28+B29+B30+B31+B33+B34+B35+B36+B37+B38+B39+B40+B42+B43+B45 -> 20645451 | C46: =C6+C7+C8+C10+C11+C12+C13+C14+C15+C17+C18+C19+C20+C21+C23+C24+C25+C26+C27+C28+C29+C30+C31+C33+C34+C35+C36+C37+C38+C39+C40+C42+C43+C45 -> 25680377 | D46: =D6+D7+D8+D10+D11+D12+D13+D14+D15+D17+D18+D19+D20+D21+D23+D24+D25+D26+D27+D28+D29+D30+D31+D33+D34+D35+D36+D37+D38+D39+D40+D42+D43+D45 -> 46325828 | E46: =E6+E7+E8+E10+E11+E12+E13+E14+E15+E17+E18+E19+E20+E21+E23+E24+E25+E26+E27+E28+E29+E30+E31+E33+E34+E35+E36+E37+E38+E39+E40+E42+E43+E45 -> #VALUE! | F46: =F6+F7+F8+F10+F11+F12+F13+F14+F15+F17+F18+F19+F20+F21+F23+F24+F25+F26+F27+F28+F29+F30+F31+F33+F34+F35+F36+F37+F38+F39+F40+F42+F43+F45 -> #VALUE! | G46: =G6+G7+G8+G10+G11+G12+G13+G14+G15+G17+G18+G19+G20+G21+G23+G24+G25+G26+G27+G28+G29+G30+G31+G33+G34+G35+G36+G37+G38+G39+G40+G42+G43+G45 -> #VALUE! | H46: =H6+H7+H8+H10+H11+H12+H13+H14+H15+H17+H18+H19+H20+H21+H23+H24+H25+H26+H27+H28+H29+H30+H31+H33+H34+H35+H36+H37+H38+H39+H40+H42+H43+H45 -> #VALUE! | I46: =I6+I7+I8+I10+I11+I12+I13+I14+I15+I17+I18+I19+I20+I21+I23+I24+I25+I26+I27+I28+I29+I30+I31+I33+I34+I35+I36+I37+I38+I39+I40+I42+I43+I45 -> #VALUE! | ... K46: =K6+K7+K8+K10+K11+K12+K13+K14+K15+K17+K18+K19+K20+K21+K23+K24+K25+K26+K27+K28+K29+K30+K31+K33+K34+K35+K36+K37+K38+K39+K40+K42+K43+K45 -> 58126321
A47: Not allocated to class | B47: ='TAM summary'!E5-B46 -> -823451 | C47: ='TAM summary'!F5-C46 -> 826623 | D47: ='TAM summary'!G5-D46 -> 172 | E47: ='TAM summary'!G6-E46 -> #VALUE! | F47: ='TAM summary'!G7-F46 -> #VALUE! | G47: ='TAM summary'!G8-G46 -> #VALUE! | H47: ='TAM summary'!G9-H46 -> #VALUE! | I47: ='TAM summary'!G10-I46 -> #VALUE! | J47: ='TAM summary'!G11-J46 -> #VALUE! | K47: =SUM(D47:J47) -> #VALUE!
A48: Total | B48: ='TAM summary'!E5 -> 19822000 | C48: ='TAM summary'!F5 -> 26507000 | D48: ='TAM summary'!G5 -> 46326000 | E48: ='TAM summary'!G6 -> 13617194 | F48: ='TAM summary'!G7 -> 2234715 | G48: ='TAM summary'!G8 -> 6624111 | H48: ='TAM summary'!G9 -> 2492740 | I48: ='TAM summary'!G10 -> 3411003 | J48: ='TAM summary'!G11 -> 227776 | K48: =SUM(D48:J48) -> 74933539
A49: QA Check | B49: =IF(ABS(B48-'TAM summary'!E5)<1,"PASS","FAIL") -> PASS | C49: =IF(ABS(C48-'TAM summary'!F5)<1,"PASS","FAIL") -> PASS | D49: =IF(ABS(D48-'TAM summary'!G5)<1,"PASS","FAIL") -> PASS | E49: =IF(ABS(E48-'TAM summary'!G6)<1,"PASS","FAIL") -> PASS | F49: =IF(ABS(F48-'TAM summary'!G7)<1,"PASS","FAIL") -> PASS | G49: =IF(ABS(G48-'TAM summary'!G8)<1,"PASS","FAIL") -> PASS | H49: =IF(ABS(H48-'TAM summary'!G9)<1,"PASS","FAIL") -> PASS | I49: =IF(ABS(I48-'TAM summary'!G10)<1,"PASS","FAIL") -> PASS | J49: =IF(ABS(J48-'TAM summary'!G11)<1,"PASS","FAIL") -> PASS

Sheet All line items
A1: All line items
A2: Master list of all extracted line items across all seven buckets
A3: All figures in USD thousands ($K)
A4: Source | B4: Line Item | C4: Vessel Class | D4: Bucket | E4: Performer | F4: FY24 | G4: FY25 | H4: FY26 Total | I4: Confidence | J4: Notes
A5: SCN L1+L2 | B5: Columbia Class (ship + AP) | C5: SSBN (Columbia) | D5: 1 | E5: GD Electric Boat / HII NNS | F5: 0 | G5: 9580774 | H5: 10920486 | I5: High | J5: FY24 zero = no new TOA
A6: SCN L8+L9 | B6: Virginia Class (ship + AP) | C6: SSN (Virginia) | D6: 1 | E6: GD Electric Boat / HII NNS | F6: 10656927 | G6: 13320211 | H6: 11078029 | I6: High | J6: FY26: $4.8B Req + $6.3B OBBA
A7: SCN L5+L6+L7 | B7: CVN-81 Carrier Replacement | C7: CVN (Ford) | D7: 1 | E7: HII Newport News | F7: 2529513 | G7: 2034054 | H7: 3281673 | I7: High | J7: CVN-80 SFF + CVN-81 ramp
A8: SCN L13+L14 | B8: DDG-51 (ship + AP) | C8: DDG-51 (Flt III) | D8: 1 | E8: HII Ingalls / GD BIW | F8: 6366431 | G8: 8268628 | H8: 5410773 | I8: High | J8: FY26: $11K Req + $5.4B OBBA
A9: SCN L12 | B9: DDG-1000 Completion | C9: DDG-1000 | D9: 1 | E9: GD Bath Iron Works | F9: 392892 | G9: 61100 | H9: 52358 | I9: High | J9: Completion/CPS only
A10: SCN L16 | B10: FFG-62 Constellation | C10: FFG-62 | D10: 1 | E10: Marinette Marine | F10: 2183861 | G10: 633200 | H10: 0 | I10: High | J10: No FY26 funding
A11: SCN L15 | B11: LCS Completion | C11: LCS | D11: 1 | E11: Austal USA / LM | F11: 23000 | G11: 48000 | H11: 0 | I11: High | J11: Program ending
A12: SCN L19+L20+L21 | B12: LPD Flight II | C12: LPD | D12: 1 | E12: HII Ingalls | F12: 516520 | G12: 1581121 | H12: 2600000 | I12: High | J12: FY26 entirely OBBA
A13: SCN L24+L25 | B13: LHA Replacement | C13: LHA | D13: 1 | E13: HII Ingalls | F13: 1830149 | G13: 176515 | H13: 3895000 | I13: High | J13: FY26 entirely OBBA
A14: SCN L27 | B14: Medium Landing Ship | C14: LSM | D14: 1 | E14: TBD | F14: 0 | G14: 29668 | H14: 1963941 | I14: High | J14: 9-ship block buy in OBBA
A15: SCN L31 | B15: T-AO Fleet Oiler | C15: T-AO | D15: 1 | E15: GD NASSCO | F15: 938315 | G15: 227154 | H15: 1861705 | I15: High | J15: FY26: $8K Req + $1.85B OBBA
A16: SCN L34 | B16: TAGOS Surtass Ships | C16: T-AGOS | D16: 1 | E16: TBD | F16: 513466 | G16: 0 | H16: 612205 | I16: High
A17: SCN L35 | B17: ATS (Towing/Salvage) | C17: ATS | D17: 1 | E17: TBD | F17: 22959 | G17: 82587 | H17: 0 | I17: High | J17: Completion only
A18: SCN L37 | B18: Oceanographic Ships | C18: T-AGS | D18: 1 | E18: TBD | F18: 0 | G18: 18000 | H18: 0 | I18: High | J18: Completion only
A19: SCN L39 | B19: LCU 1700 | C19: LCU | D19: 1 | E19: TBD | F19: 62532 | G19: 0 | H19: 295000 | I19: High | J19: FY26 OBBA: 9 craft
A20: SCN L40 | B20: Strategic Sealift | C20: Sealift | D20: 1 | E20: TBD | F20: 0 | G20: 0 | H20: 600000 | I20: High | J20: FY26 OBBA
A21: SCN L42 | B21: Ship to Shore Connector | C21: SSC | D21: 1 | E21: Textron | F21: 628600 | G21: 528039 | H21: 239095 | I21: High | J21: LCAC replacement
A22: SCN L43 | B22: Service Craft | C22: Various | D22: 1 | E22: Various | F22: 93815 | G22: 41426 | H22: 34602 | I22: High
A23: SCN L44 | B23: Aux Personnel Lighter | C23: APL | D23: 1 | E23: TBD | F23: 72000 | G23: 76168 | H23: 0 | I23: High
A24: SCN L48 | B24: Auxiliary Vessels (Used Sealift) | C24: Sealift | D24: 1 | E24: Various | F24: 142008 | G24: 204939 | H24: 145000 | I24: High | J24: Used vessel acquisition
A25: SCN L41 | B25: Outfitting (all newbuild) | C25: Multi-class | D25: 1 | E25: Various | F25: 512019 | G25: 585967 | H25: 887295 | I25: High | J25: Post-delivery outfitting
A26: SCN L49 | B26: PY Completion (Bucket 1 share) | C26: Multi-class | D26: 1 | E26: Various | F26: 0 | G26: 0 | H26: 1192266 | I26: High | J26: CTC minus RCOH/LCAC
A27: USCG PC&I | B27: Offshore Patrol Cutter | C27: CG: OPC | D27: 1 | E27: Eastern Shipbuilding | F27: 579000 | G27: 579000 | H27: 812400 | I27: High | J27: OPCs #8-9; LLTM #10-11
A28: USCG PC&I | B28: Fast Response Cutter | C28: CG: FRC | D28: 1 | E28: Bollinger | F28: 220000 | G28: 220000 | H28: 216000 | I28: High | J28: FRCs #62-64
A29: USCG PC&I | B29: Polar Security Cutter | C29: CG: PSC | D29: 1 | E29: Bollinger | F29: 0 | G29: 0 | H29: 130000 | I29: High | J29: PSC #1 construction
A30: USCG PC&I | B30: Waterways Commerce Cutter | C30: CG: WCC | D30: 1 | E30: TBD | F30: 1000 | G30: 1000 | H30: 98000 | I30: High
A31: USCG PC&I | B31: NSC Completion | C31: CG: NSC | D31: 1 | E31: HII Ingalls | F31: 17100 | G31: 17100 | H31: 0 | I31: High | J31: Complete after FY25
A32: USCG PC&I | B32: Commercial Polar Icebreaker | C32: CG: Icebreaker | D32: 1 | E32: Commercial | F32: 125000 | G32: 125000 | H32: 0 | I32: High | J32: CGC Storis acquisition
A33: USCG PC&I | B33: Great Lakes Icebreaker | C33: CG: Icebreaker | D33: 1 | E33: TBD | F33: 20000 | G33: 20000 | H33: 0 | I33: High
A34: OMN 1B4B | B34: Ship Modernization Program (SMP) | C34: Multi-class | D34: 2 | E34: Mixed | F34: 1203816 | G34: 869253 | H34: 1197180 | I34: High
A35: OMN 1B4B | B35: NME / 2-Hatch Ships | C35: Multi-class | D35: 2 | E35: Mixed | F35: 1197197 | G35: 1306411 | H35: 1341155 | I35: High
A36: OMN 1B4B | B36: NME / 4-Hatch Ships | C36: Multi-class | D36: 2 | E36: Mixed | F36: 1247653 | G36: 1290155 | H36: 1289894 | I36: High
A37: OMN 1B4B | B37: NME / Submarine Availability | C37: SSN/SSBN | D37: 2 | E37: Public Yard | F37: 871537 | G37: 896253 | H37: 924629 | I37: High | J37: Primarily NNSY/PHNSY
A38: OMN 1B4B | B38: NME / Industrial Base | C38: Multi-class | D38: 2 | E38: Mixed | F38: 1245621 | G38: 1270256 | H38: 1267865 | I38: High
A39: OMN 1B4B | B39: NME / NAVPLAN | C39: Multi-class | D39: 2 | E39: Mixed | F39: 1134835 | G39: 1139556 | H39: 1134328 | I39: High
A40: OMN 1B4B | B40: NME / SSN-to-Repair | C40: SSN/SSBN | D40: 2 | E40: Public Yard | F40: 630555 | G40: 639229 | H40: 642190 | I40: High | J40: Public yard sub repair
A41: OMN 1B4B | B41: NME / Carrier | C41: CVN | D41: 2 | E41: Mixed | F41: 762048 | G41: 816344 | H41: 784000 | I41: High
A42: OMN 1B4B | B42: NME / Amphibious | C42: Amphibious | D42: 2 | E42: Private | F42: 569696 | G42: 656000 | H42: 624506 | I42: High
A43: OMN 1B4B | B43: NME / LCS | C43: LCS | D43: 2 | E43: Private | F43: 481854 | G43: 539000 | H43: 492493 | I43: High
A44: OMN 1B4B | B44: NME / DDG | C44: DDG-51 | D44: 2 | E44: Private | F44: 758318 | G44: 758610 | H44: 749000 | I44: High
A45: OMN 1B4B | B45: MSC M&R (transfer from NWCF) | C45: MSC Fleet | D45: 2 | E45: Private | F45: 0 | G45: 0 | H45: 1584000 | I45: Medium | J45: New FY26 transfer
A46: OMN 1B4B | B46: Residual NME rounding | C46: Multi-class | D46: 2 | E46: Mixed | F46: 0 | G46: 0 | H46: -176024 | I46: Low | J46: SAG total controls
A47: OPN BA1 | B47: L26 Ship Maint, Repair & Mod | C47: Multi-class | D47: 2 | E47: Private | F47: 2839179 | G47: 2392190 | H47: 2392620 | I47: High | J47: OPN material for depot
A48: USCG O&S | B48: Bucket 2 share (60% of O&S 25.7) | C48: CG: fleet | D48: 2 | E48: Mixed | F48: 329409 | G48: 335840 | H48: 369358 | I48: Medium | J48: Analyst 60% allocation
A49: OMN 1B4B | B49: CMMP (Continuous Maint & Mod) | C49: Multi-class | D49: 3 | E49: Mixed | F49: 1259925 | G49: 1303227 | H49: 1321948 | I49: High
A50: OMN 1B4B | B50: Expedited M&M | C50: Multi-class | D50: 3 | E50: Mixed | F50: 581796 | G50: 602706 | H50: 640000 | I50: High
A51: OMN 1B5B | B51: RMC | C51: Multi-class | D51: 3 | E51: Mixed | F51: 22311 | G51: 25633 | H51: 26529 | I51: High | J51: Regional Maint Centers
A52: USCG O&S | B52: Bucket 3 share (40% of O&S 25.7) | C52: CG: fleet | D52: 3 | E52: Mixed | F52: 219606 | G52: 223893 | H52: 246238 | I52: Medium | J52: Analyst 40% allocation
A53: OPN BA1 | B53: L1 Surface Power Equipment | C53: Multi-class | D53: 4 | E53: Private | F53: 12855 | G53: 20840 | H53: 9978 | I53: High
A54: OPN BA1 | B54: L2 Surface Combatant HM&E | C54: Multi-class | D54: 4 | E54: Private | F54: 92449 | G54: 77592 | H54: 62004 | I54: High
A55: OPN BA1 | B55: L4 Sub Periscope/Imaging | C55: SSN/SSBN | D55: 4 | E55: Mixed | F55: 272778 | G55: 290575 | H55: 277413 | I55: High
A56: OPN BA1 | B56: L5 DDG Mod | C56: DDG-51 | D56: 4 | E56: Private | F56: 641676 | G56: 861066 | H56: 997485 | I56: High
A57: OPN BA1 | B57: L8 LHA/LHD Midlife | C57: LHA/LHD | D57: 4 | E57: Private | F57: 102334 | G57: 81602 | H57: 123384 | I57: High
A58: OPN BA1 | B58: L11 Submarine Support Equipment | C58: SSN/SSBN | D58: 4 | E58: Mixed | F58: 210652 | G58: 293766 | H58: 383062 | I58: High
A59: OPN BA1 | B59: L12 Virginia Class Support | C59: SSN (Virginia) | D59: 4 | E59: Mixed | F59: 32055 | G59: 43565 | H59: 52039 | I59: High
A60: OPN BA1 | B60: L13 LCS Class Support | C60: LCS | D60: 4 | E60: Private | F60: 17816 | G60: 7318 | H60: 2551 | I60: High | J60: Declining
A61: OPN BA1 | B61: L15 LPD Class Support | C61: LPD | D61: 4 | E61: Private | F61: 80933 | G61: 38115 | H61: 125542 | I61: High
A62: OPN BA1 | B62: L16 DDG-1000 Class Support | C62: DDG-1000 | D62: 4 | E62: Private | F62: 220771 | G62: 340668 | H62: 115267 | I62: High
A63: OPN BA1 | B63: L17 Strategic Platform Support | C63: SSN/SSBN | D63: 4 | E63: Mixed | F63: 23756 | G63: 53931 | H63: 53740 | I63: High
A64: OPN BA1 | B64: L21 LCAC | C64: SSC/LCAC | D64: 4 | E64: Private | F64: 10239 | G64: 11013 | H64: 20321 | I64: High
A65: OPN BA1 | B65: L28 Reactor Components | C65: Multi-class | D65: 4 | E65: Mixed | F65: 389890 | G65: 445974 | H65: 399603 | I65: High | J65: Subs + carriers
A66: OPN BA1 | B66: L33 LCS Common Mission Modules | C66: LCS | D66: 4 | E66: Private | F66: 49028 | G66: 56105 | H66: 38880 | I66: High
A67: OPN BA1 | B67: L34 LCS MCM Mission Modules | C67: LCS | D67: 4 | E67: Private | F67: 87828 | G67: 118247 | H67: 91372 | I67: High
A68: OPN BA1 | B68: L36 LCS SUW Mission Modules | C68: LCS | D68: 4 | E68: Private | F68: 12094 | G68: 11101 | H68: 3790 | I68: High
A69: OPN BA1 | B69: L37 LCS In-Service Mod | C69: LCS | D69: 4 | E69: Private | F69: 154561 | G69: 188254 | H69: 237728 | I69: High
A70: OPN BA1 | B70: L40 LSD Midlife & Mod | C70: LSD | D70: 4 | E70: Private | F70: 3989 | G70: 56667 | H70: 4079 | I70: High
A71: OPN BA2 | B71: L43 AN/SQQ-89 | C71: Multi-class | D71: 4 | E71: Private | F71: 133803 | G71: 134637 | H71: 144425 | I71: High | J71: DDG/CG sonar
A72: OPN BA2 | B72: L44 SSN Acoustic (80%) | C72: SSN/SSBN | D72: 4 | E72: Mixed | F72: 107116 | G72: 117310 | H72: 398878 | I72: Medium | J72: 80% in-service share
A73: OPN BA2 | B73: L46 Sub Acoustic Warfare | C73: SSN/SSBN | D73: 4 | E73: Mixed | F73: 41695 | G73: 51514 | H73: 56482 | I73: High
A74: OPN BA2 | B74: L50 AN/SLQ-32 SEWIP | C74: Multi-class | D74: 4 | E74: Private | F74: 325996 | G74: 182011 | H74: 461380 | I74: High
A75: OPN BA2 | B75: L51 Shipboard IW Exploit | C75: Multi-class | D75: 4 | E75: Mixed | F75: 367452 | G75: 362099 | H75: 379908 | I75: High
A76: OPN BA2 | B76: L53 CEC (95%) | C76: Multi-class | D76: 4 | E76: Private | F76: 22776 | G76: 23696 | H76: 25316 | I76: Medium
A77: OPN BA2 | B77: L70 CANES (99%) | C77: Multi-class | D77: 4 | E77: Mixed | F77: 416879 | G77: 413558 | H77: 530408 | I77: Medium
A78: OPN BA2 | B78: L72 CANES-Intell (99%) | C78: Multi-class | D78: 4 | E78: Mixed | F78: 38283 | G78: 40128 | H78: 45813 | I78: Medium
A79: OPN BA2 | B79: L78 In-Service Radars/Sensors | C79: Multi-class | D79: 4 | E79: Private | F79: 279545 | G79: 222607 | H79: 249656 | I79: High
A80: OPN BA2 | B80: L79 Battle Force Tactical Net | C80: Multi-class | D80: 4 | E80: Mixed | F80: 68327 | G80: 104119 | H80: 106583 | I80: High
A81: OPN BA2 | B81: L80 Shipboard Tactical Comms (90%) | C81: Multi-class | D81: 4 | E81: Mixed | F81: 14440 | G81: 15480 | H81: 18810 | I81: Medium
A82: OPN BA2 | B82: L81 Ship Comms Automation (75%) | C82: Multi-class | D82: 4 | E82: Mixed | F82: 96000 | G82: 100800 | H82: 121556 | I82: Medium
A83: OPN BA4 | B83: BLI 125 Ship Gun Systems | C83: Multi-class | D83: 4 | E83: Private | F83: 16250 | G83: 6416 | H83: 7358 | I83: High
A84: OPN BA4 | B84: BLI 126 Harpoon | C84: Multi-class | D84: 4 | E84: Mixed | F84: 227 | G84: 226 | H84: 209 | I84: High
... A91: OPN BA4 | B91: BLI 136 Anti-Ship Missile Decoy | C91: Multi-class | D91: 4 | E91: Mixed | F91: 51100 | G91: 75614 | H91: 89129 | I91: High
A92: USCG PC&I | B92: ISSS | C92: CG: fleet | D92: 4 | E92: Mixed | F92: 25000 | G92: 28000 | H92: 30000 | I92: Medium | J92: In-Service Ship Systems
A93: USCG PC&I | B93: C4ISR | C93: CG: fleet | D93: 4 | E93: Mixed | F93: 16000 | G93: 16000 | H93: 10000 | I93: Medium
A94: USCG PC&I | B94: Cyber/EMP (50% vessel share) | C94: CG: fleet | D94: 4 | E94: Mixed | F94: 10000 | G94: 11000 | H94: 12900 | I94: Low
A95: SCN | B95: CVN RCOH SFF (CVN 75) | C95: CVN | D95: 5 | E95: HII-NNS | F95: 0 | G95: 811143 | H95: 1779011 | I95: High
A96: SCN | B96: CVN RCOH CTC (CVN 74) | C96: CVN | D96: 5 | E96: HII-NNS | F96: 42422 | G96: 669171 | H96: 483100 | I96: High
A97: SCN | B97: CVN RCOH Outfitting | C97: CVN | D97: 5 | E97: Private | F97: 19704 | G97: 6660 | H97: 12200 | I97: High
A98: SCN | B98: LCAC SLEP (ESLEP) | C98: SSC/LCAC | D98: 5 | E98: Walashek | F98: 15286 | G98: 45087 | H98: 37390 | I98: High
A99: SCN | B99: LCAC SLEP Outfitting | C99: SSC/LCAC | D99: 5 | E99: Private | F99: 728 | G99: 0 | H99: 493 | I99: High
A100: OPN BA1 | B100: L9 LCC ESLP | C100: LCC | D100: 5 | E100: Private | F100: 10522 | G100: 7352 | H100: 19276 | I100: High
A101: USCG PC&I | B101: 47-ft MLB SLEP | C101: CG: MLB | D101: 5 | E101: CG Yard/Private | F101: 43000 | G101: 43000 | H101: 45000 | I101: Medium
A102: USCG PC&I | B102: 270-ft WMEC SLEP | C102: CG: WMEC | D102: 5 | E102: CG Yard | F102: 46200 | G102: 46200 | H102: 76000 | I102: Medium
A103: USCG PC&I | B103: 175-ft WLM MMA | C103: CG: WLM | D103: 5 | E103: CG Yard | F103: 17800 | G103: 17800 | H103: 15000 | I103: Medium
A104: USCG PC&I | B104: CGC Healy SLEP | C104: CG: Healy | D104: 5 | E104: Mixed | F104: 13000 | G104: 13000 | H104: 11000 | I104: Medium
A105: USCG PC&I | B105: 418-ft WMSL MMA | C105: CG: WMSL | D105: 5 | E105: CG Yard | F105: 0 | G105: 0 | H105: 5000 | I105: Low | J105: New FY26
A106: USCG PC&I | B106: Boats RB-M SLEP portion | C106: CG: RB-M | D106: 5 | E106: Private | F106: 1950 | G106: 1950 | H106: 9270 | I106: Low
...

Sheet PB-61 detail
A1: PB-61 detail
A2: PB-61 Depot Maintenance Summary — per-class detail from OMN Vol2
A3: All figures in USD thousands ($K)
A5: OMN — Ship Maint (Bucket 2)
A6: Weapon System | B6: FY24 Total | C6: FY25 Funded | D6: FY25 Required | E6: FY25 % | F6: FY26 Funded | G6: FY26 Required | H6: FY26 %
A7: CV-CVN | B7: 1796346 | C7: 2748996 | D7: 2897547 | E7: 0.95 | F7: 2720122 | G7: 3030280 | H7: 0.9
A8: CV-CVN (SRB) | B8: 278 | C8: 312 | D8: 312 | E8: 1 | F8: 312 | G8: 323 | H8: 0.97
A9: CVN | B9: 0 | C9: 0 | D9: 0 | E9: N/A | F9: 17657 | G9: 18054 | H9: 0.98
A10: DDG | B10: 732057 | C10: 563674 | D10: 595584 | E10: 0.95 | F10: 525288 | G10: 568246 | H10: 0.92
A11: DDG-1000 | B11: 0 | C11: 0 | D11: 0 | E11: N/A | F11: 6174 | G11: 7358 | H11: 0.84
A12: SSN-MTS-SSGN | B12: 2524018 | C12: 2635557 | D12: 2765819 | E12: 0.95 | F12: 2431863 | G12: 2531177 | H12: 0.96
A13: SSN-SSGN | B13: 1964943 | C13: 1633867 | D13: 1758233 | E13: 0.93 | F13: 1410798 | G13: 1598434 | H13: 0.88
A14: SSN | B14: 94867 | C14: 126352 | D14: 126352 | E14: 1 | F14: 584293 | G14: 592946 | H14: 0.99
A15: SSBN | B15: 424396 | C15: 276204 | D15: 276424 | E15: 1 | F15: 301080 | G15: 307425 | H15: 0.98
A16: SSGN | B16: 0 | C16: 0 | D16: 0 | E16: N/A | F16: 67781 | G16: 67846 | H16: 1
A17: AMPHIBS | B17: 518125 | C17: 474175 | D17: 499230 | E17: 0.95 | F17: 180719 | G17: 223014 | H17: 0.81
A18: LCS | B18: 241434 | C18: 225747 | D18: 237189 | E18: 0.95 | F18: 230789 | G18: 346046 | H18: 0.67
A19: LPD | B19: 0 | C19: 0 | D19: 0 | E19: N/A | F19: 105286 | G19: 105354 | H19: 1
A20: LHA | B20: 0 | C20: 0 | D20: 0 | E20: N/A | F20: 29116 | G20: 30946 | H20: 0.94
A21: LHD | B21: 0 | C21: 0 | D21: 0 | E21: N/A | F21: 36577 | G21: 37210 | H21: 0.98
A22: LSD | B22: 0 | C22: 0 | D22: 0 | E22: N/A | F22: 73346 | G22: 97543 | H22: 0.75
A23: CG | B23: 106091 | C23: 50328 | D23: 51680 | E23: 0.97 | F23: 40292 | G23: 42503 | H23: 0.95
A24: ESB | B24: 6850 | C24: 20241 | D24: 20629 | E24: 0.98 | F24: 19655 | G24: 22134 | H24: 0.89
A25: LCC | B25: 5496 | C25: 517 | D25: 517 | E25: 1 | F25: 3899 | G25: 57265 | H25: 0.07
A26: AGF-LCC | B26: 15372 | C26: 65480 | D26: 65674 | E26: 1 | F26: 2762 | G26: 3093 | H26: 0.89
A27: MCM-MHC | B27: 55837 | C27: 46252 | D27: 47028 | E27: 0.98 | F27: 10813 | G27: 13189 | H27: 0.82
A28: SOH | B28: 13902 | C28: 27805 | D28: 27805 | E28: 1 | F28: 27382 | G28: 29120 | H28: 0.94
A29: ARDM-AS | B29: 1903 | C29: 89284 | D29: 89284 | E29: 1 | F29: 24967 | G29: 24967 | H29: 1
A30: AS-ARDM | B30: 17244 | C30: 23306 | D30: 23632 | E30: 0.99 | F30: 8400 | G30: 8751 | H30: 0.96
A32: OMN — Continuous Maintenance (Bucket 3)
A33: Weapon System | B33: FY24 Total | C33: FY25 Funded | D33: FY25 Required | E33: FY25 % | F33: FY26 Funded | G33: FY26 Required | H33: FY26 %
A34: DDG | B34: 106432 | C34: 100690 | D34: 100690 | E34: 1 | F34: 123497 | G34: 123497 | H34: 1
A35: LCS | B35: 60812 | C35: 69375 | D35: 69375 | E35: 1 | F35: 69759 | G35: 69759 | H35: 1
A36: CG | B36: 3066 | C36: 5200 | D36: 5200 | E36: 1 | F36: 5969 | G36: 5969 | H36: 1
A37: DDG-1000 | B37: 0 | C37: 3950 | D37: 3950 | E37: 1 | F37: 7645 | G37: 7645 | H37: 1
A38: LCAC | B38: 9219 | C38: 7720 | D38: 7720 | E38: 1 | F38: 7952 | G38: 7952 | H38: 1
A39: AMPHIBS | B39: 15037 | C39: 17188 | D39: 17188 | E39: 1 | F39: 0 | G39: 0 | H39: N/A
A40: MINESWEEPERS | B40: 370 | C40: 1620 | D40: 1620 | E40: 1 | F40: 1068 | G40: 1068 | H40: 1
A41: Other | B41: 89976 | C41: 155923 | D41: 155923 | E41: 1 | F41: 127665 | G41: 127665 | H41: 1
A43: OMN — Other Depot Maintenance
A44: Weapon System | B44: FY24 Total | C44: FY25 Funded | D44: FY25 Required | E44: FY25 % | F44: FY26 Funded | G44: FY26 Required | H44: FY26 %
A45: CV-CVN | B45: 193274 | C45: 97736 | D45: 102481 | E45: 0.95 | F45: 364463 | G45: 184318 | H45: 1.98
A46: DDG | B46: 429962 | C46: 353844 | D46: 405744 | E46: 0.87 | F46: 426684 | G46: 454399 | H46: 0.94
A47: SSBN | B47: 528266 | C47: 541600 | D47: 550579 | E47: 0.98 | F47: 577323 | G47: 604609 | H47: 0.95
A48: SSN-MTS-SSGN | B48: 356970 | C48: 233706 | D48: 258466 | E48: 0.9 | F48: 259540 | G48: 280442 | H48: 0.93
A49: SSN-SSGN | B49: 677440 | C49: 628771 | D49: 660421 | E49: 0.95 | F49: 453013 | G49: 477255 | H49: 0.95
A50: SSGN | B50: 0 | C50: 0 | D50: 0 | E50: N/A | F50: 157370 | G50: 162292 | H50: 0.97
A51: SSN | B51: 0 | C51: 0 | D51: 0 | E51: N/A | F51: 75160 | G51: 77571 | H51: 0.97
A52: CG | B52: 69927 | C52: 83031 | D52: 86340 | E52: 0.96 | F52: 75209 | G52: 77398 | H52: 0.97
A53: LCS | B53: 168387 | C53: 233021 | D53: 279807 | E53: 0.83 | F53: 345600 | G53: 372513 | H53: 0.93
A54: AMPHIBS | B54: 199393 | C54: 196703 | D54: 201922 | E54: 0.97 | F54: 112718 | G54: 150945 | H54: 0.75
A55: LPD | B55: 0 | C55: 0 | D55: 0 | E55: N/A | F55: 44309 | G55: 45312 | H55: 0.98
A56: LHA | B56: 0 | C56: 0 | D56: 0 | E56: N/A | F56: 15896 | G56: 16315 | H56: 0.97
A57: LHD | B57: 0 | C57: 0 | D57: 0 | E57: N/A | F57: 16429 | G57: 16573 | H57: 0.99
A58: LSD | B58: 0 | C58: 0 | D58: 0 | E58: N/A | F58: 21075 | G58: 21237 | H58: 0.99
A59: AEGIS ASHORE | B59: 27696 | C59: 3724 | D59: 3830 | E59: 0.97 | F59: 4275 | G59: 4244 | H59: 1.01
A60: ESB | B60: 1224 | C60: 1454 | D60: 1461 | E60: 1 | F60: 4007 | G60: 4091 | H60: 0.98
A61: MCM-MHC | B61: 26770 | C61: 24799 | D61: 24900 | E61: 1 | F61: 12468 | G61: 12585 | H61: 0.99
A62: AGF-LCC | B62: 11377 | C62: 14291 | D62: 15325 | E62: 0.93 | F62: 15511 | G62: 15683 | H62: 0.99
A64: OPN — Ship Depot Maintenance
A65: Weapon System | B65: FY24 Total | C65: FY25 Funded | D65: FY25 Required | E65: FY25 % | F65: FY26 Funded | G65: FY26 Required | H65: FY26 %
A66: DDG | B66: 1676352 | C66: 732451 | D66: 814455 | E66: N/A | F66: 1282612 | G66: 1418118 | H66: N/A
A67: LCS | B67: 110171 | C67: 232091 | D67: 232091 | E67: N/A | F67: 383361 | G67: 383361 | H67: N/A
A68: LHD | B68: 0 | C68: 0 | D68: 0 | E68: N/A | F68: 395086 | G68: 395086 | H68: N/A
A69: AMPHIBS | B69: 573902 | C69: 1097648 | D69: 1354392 | E69: N/A | F69: 236773 | G69: 393588 | H69: N/A
A70: CG | B70: 0 | C70: 0 | D70: 0 | E70: N/A | F70: 44940 | G70: 44940 | H70: N/A
A71: CV-CVN (continuous) | B71: 13102 | C71: 54832 | D71: 54832 | E71: N/A | F71: 63908 | G71: 63908 | H71: N/A
A72: SSN (continuous) | B72: 73142 | C72: 2810 | D72: 2810 | E72: N/A | F72: 53356 | G72: 53356 | H72: N/A
A73: SSN/SSGN Electronics | B73: 7736 | C73: 7398 | D73: 7398 | E73: N/A | F73: 7620 | G73: 12047 | H73: N/A
A74: SSBN/SSGN (continuous) | B74: 0 | C74: 0 | D74: 0 | E74: N/A | F74: 2669 | G74: 2669 | H74: N/A
A75: LHA | B75: 0 | C75: 0 | D75: 0 | E75: N/A | F75: 12065 | G75: 12065 | H75: N/A
A76: LPD | B76: 0 | C76: 0 | D76: 0 | E76: N/A | F76: 11852 | G76: 11852 | H76: N/A
A77: LSD | B77: 0 | C77: 0 | D77: 0 | E77: N/A | F77: 25931 | G77: 25931 | H77: N/A
A78: SSN-MTS-SSGN | B78: 383868 | C78: 330000 | D78: 330000 | E78: N/A | F78: 0 | G78: 0 | H78: N/A

Sheet Sources and methodology
A1: Sources and methodology
A2: Data sources, confidence levels, methodology notes, and reconciliation checks
A4: Source Files
A5: SCN Justification Book (PB-27) | B5: Bucket 1 new construction line items and OBBA detail
A6: OMN Vol 2 (PB-61) | B6: Buckets 2-3 depot maintenance and continuous maintenance by weapon system
A7: OPN Justification Book (PB-28) | B7: Bucket 4 modernization equipment and Bucket 2 material support
A8: USCG Capital Investment Plan | B8: Coast Guard PC&I acquisition and SLEP programs
A9: USCG O&S Budget Justification | B9: Coast Guard operations and support allocated to vessel maintenance
A10: OPN BA8 Initial Spares | B10: Bucket 6 war reserve and initial spares (BLI 9020)
A11: NAVSEA HQ / SUPSHIP data | B11: Bucket 6 sustainment engineering and planning overhead
A13: Confidence Levels
A14: High | B14: Direct budget line item with no estimation or allocation required
A15: Medium | B15: Derived from budget data with minor analyst allocation (e.g., percentage split)
A16: Low | B16: Analyst estimate based on historical patterns, indirect evidence, or proxy data
A18: Key Methodology Notes
A19: 1. All figures are in USD thousands ($K) unless otherwise noted.
A20: 2. FY26 OBBA (Off-Budget Baseline Adjustment) reflects supplemental shipbuilding funding in the NDAA.
A21: 3. Coast Guard O&S is split 60/40 between Bucket 2 (depot) and Bucket 3 (continuous) based on analyst estimate.
A22: 4. OPN lines with partial vessel share (e.g., 80%, 95%) reflect analyst allocation of ship-applicable portion.
A23: 5. MSC M&R ($1.584B) is a new FY26 transfer from Navy Working Capital Fund and was not in FY24-25 baselines.
A24: 6. PY Completion (prior-year) is split between Bucket 1 (newbuild) and Bucket 5 (RCOH/SLEP) based on program detail.
A25: 7. Residual NME rounding line in Bucket 2 is a balancing entry to match the SAG-level control total.
A26: 8. Bucket 7 (Availability Support) captures port services, berthing, and facility support not included in depot events.
A28: Annotation Key
A29: N/A | B29: Budget source does not break this data out by vessel class for this bucket
A30: — (dash) | B30: Genuine zero value; the number format renders 0 as a dash
A31: Blue text | B31: Hardcoded numeric input from budget documents
A32: Green text | B32: Cross-tab formula linking to another worksheet
A33: Gray text | B33: Source references, notes, or analyst annotations
A35: Reconciliation Checks
A36: Bucket | B36: Tab 1 Value | C36: Tab 2 Column Total | D36: Delta | E36: Status
A37: Bucket 1 (New Construction) | B37: ='TAM summary'!G5 -> 46326000 | C37: ='By vessel class'!D46 -> 46325828 | D37: =B37-C37 -> 172 | E37: =IF(ABS(D37)<1,"PASS","FAIL") -> FAIL
A38: Bucket 2 (Scheduled Depot Maint) | B38: ='TAM summary'!G6 -> 13617194 | C38: ='By vessel class'!E46 -> #VALUE! | D38: =B38-C38 -> #VALUE! | E38: =IF(ABS(D38)<1,"PASS","FAIL") -> #VALUE!
A39: Bucket 3 (Continuous/Intermediate) | B39: ='TAM summary'!G7 -> 2234715 | C39: ='By vessel class'!F46 -> #VALUE! | D39: =B39-C39 -> #VALUE! | E39: =IF(ABS(D39)<1,"PASS","FAIL") -> #VALUE!
A40: Bucket 4 (Modernization) | B40: ='TAM summary'!G8 -> 6624111 | C40: ='By vessel class'!G46 -> #VALUE! | D40: =B40-C40 -> #VALUE! | E40: =IF(ABS(D40)<1,"PASS","FAIL") -> #VALUE!
A41: Bucket 5 (Major Life-Cycle) | B41: ='TAM summary'!G9 -> 2492740 | C41: ='By vessel class'!H46 -> #VALUE! | D41: =B41-C41 -> #VALUE! | E41: =IF(ABS(D41)<1,"PASS","FAIL") -> #VALUE!
A42: Bucket 6 (Sustainment Eng) | B42: ='TAM summary'!G10 -> 3411003 | C42: ='By vessel class'!I46 -> #VALUE! | D42: =B42-C42 -> #VALUE! | E42: =IF(ABS(D42)<1,"PASS","FAIL") -> #VALUE!
A43: Bucket 7 (Availability Support) | B43: ='TAM summary'!G11 -> 227776 | C43: ='By vessel class'!J46 -> #VALUE! | D43: =B43-C43 -> #VALUE! | E43: =IF(ABS(D43)<1,"PASS","FAIL") -> #VALUE!
